[{"sms_id": 2170721137043, "sms_message": "Oh thank you for replying. Which pizza restaurant?can you describe  more information about this restaurant?", "to_name": "Duncan Hunter", "to_location": "Calgary, AB", "to_availability": "Alive", "from_name": null, "from_phone_nuber": "+16393189639", "from_location": null, "sms_message_type": "SMS", "sms_delivery_status": "Received", "sms_direction": "Inbound", "sms_read_status": "Read", "sms_priority": "Normal", "sms_time": "2023-10-05T21:07:06.000Z", "sms_time_modified": "2023-10-05T21:07:07.415Z", "conversation_id": 827655989706765700, "conversation_uri": "https://platform.ringcentral.com/restapi/v1.0/conversation/827655989706765734"}, {"sms_id": 2170720790043, "sms_message": "Hi Haiou, it's Mary, I was calling with Re/Max Premier Realty and FindBusinesses4Sale, checking about your inquiry for a Pizza Restaurant for Sale ", "to_name": null, "to_location": null, "to_availability": "Alive", "from_name": "Duncan Hunter", "from_phone_nuber": "+15873320613", "from_location": "Calgary, AB", "sms_message_type": "SMS", "sms_delivery_status": "Delivered", "sms_direction": "Outbound", "sms_read_status": "Read", "sms_priority": "Normal", "sms_time": "2023-10-05T21:04:33.000Z", "sms_time_modified": "2023-10-05T21:04:35.710Z", "conversation_id": 827655989706765700, "conversation_uri": "https://platform.ringcentral.com/restapi/v1.0/conversation/827655989706765734"}, {"sms_id": 2170693696043, "sms_message": "Hey Gabbie!\n\nMary here with Re/Max Premier Realty and FindBusinesses4Sale, we\u00c2\u00b4re a Canadian Business Marketplace.\n\nI have just left you a Voicemail.\n\nPlease contact me using this number when you are free:\n(587) 332-0613\n\nThanks!", "to_name": null, "to_location": null, "to_availability": "Alive", "from_name": "Duncan Hunter", "from_phone_nuber": "+15873320613", "from_location": "Calgary, AB", "sms_message_type": "SMS", "sms_delivery_status": "Delivered", "sms_direction": "Outbound", "sms_read_status": "Read", "sms_priority": "Normal", "sms_time": "2023-10-05T18:25:34.000Z", "sms_time_modified": "2023-10-05T18:25:36.429Z", "conversation_id": 827707988393430400, "conversation_uri": "https://platform.ringcentral.com/restapi/v1.0/conversation/827707988393430395"}, {"sms_id": 2170688083043, "sms_message": "Hey Roger! Thank you for the heads up, let me check with my realtor what's going on and I will be right back to you ", "to_name": null, "to_location": "Calgary, AB", "to_availability": "Alive", "from_name": "Duncan Hunter", "from_phone_nuber": "+15873320613", "from_location": "Calgary, AB", "sms_message_type": "SMS", "sms_delivery_status": "Delivered", "sms_direction": "Outbound", "sms_read_status": "Read", "sms_priority": "Normal", "sms_time": "2023-10-05T17:58:07.000Z", "sms_time_modified": "2023-10-05T17:58:09.444Z", "conversation_id": 895922426642448300, "conversation_uri": "https://platform.ringcentral.com/restapi/v1.0/conversation/895922426642448276"}, {"sms_id": 2170687028043, "sms_message": "Hello, I didn't receive any call back from the realtor yet. Please show me details of the deal ", "to_name": "Duncan Hunter", "to_location": "Calgary, AB", "to_availability": "Alive", "from_name": null, "from_phone_nuber": "+14034724195", "from_location": "Calgary, AB", "sms_message_type": "SMS", "sms_delivery_status": "Received", "sms_direction": "Inbound", "sms_read_status": "Read", "sms_priority": "Normal", "sms_time": "2023-10-05T17:52:20.000Z", "sms_time_modified": "2023-10-05T17:52:35.607Z", "conversation_id": 895922426642448300, "conversation_uri": "https://platform.ringcentral.com/restapi/v1.0/conversation/895922426642448276"}, {"sms_id": 2170685927043, "sms_message": "Hey Hussein!\n\nMary here with Re/Max Premier Realty and FindBusinesses4Sale, we\u00c2\u00b4re a Canadian Business Marketplace.\n\nI have just left you a Voicemail.\n\nPlease contact me using this number when you are free:\n(587) 332-0613\n\nThanks!", "to_name": null, "to_location": null, "to_availability": "Alive", "from_name": "Duncan Hunter", "from_phone_nuber": "+15873320613", "from_location": "Calgary, AB", "sms_message_type": "SMS", "sms_delivery_status": "Delivered", "sms_direction": "Outbound", "sms_read_status": "Read", "sms_priority": "Normal", "sms_time": "2023-10-05T17:46:15.000Z", "sms_time_modified": "2023-10-05T17:46:16.934Z", "conversation_id": 1083911898724979000, "conversation_uri": "https://platform.ringcentral.com/restapi/v1.0/conversation/1083911898724978935"}, {"sms_id": 2170685064043, "sms_message": "Hey Kal!\n\nMary here with Re/Max Premier Realty and FindBusinesses4Sale, we\u00c2\u00b4re a Canadian Business Marketplace.\n\nI have just left you a Voicemail.\n\nPlease contact me using this number when you are free:\n(587) 332-0613.\n\nThanks!", "to_name": null, "to_location": null, "to_availability": "Alive", "from_name": "Duncan Hunter", "from_phone_nuber": "+15873320613", "from_location": "Calgary, AB", "sms_message_type": "SMS", "sms_delivery_status": "Delivered", "sms_direction": "Outbound", "sms_read_status": "Read", "sms_priority": "Normal", "sms_time": "2023-10-05T17:41:52.000Z", "sms_time_modified": "2023-10-05T17:41:54.338Z", "conversation_id": 827651565443323400, "conversation_uri": "https://platform.ringcentral.com/restapi/v1.0/conversation/827651565443323448"}, {"sms_id": 2170684629043, "sms_message": "Hey Aras!\n\nMary here with Re/Max Premier Realty and FindBusinesses4Sale, we\u00c2\u00b4re a Canadian Business Marketplace.\n\nI have just left you a Voicemail.\n\nPlease contact me using this number when you are free:\n(587) 332-0613\n\nThanks!", "to_name": null, "to_location": "Vancouver, BC", "to_availability": "Alive", "from_name": "Duncan Hunter", "from_phone_nuber": "+15873320613", "from_location": "Calgary, AB", "sms_message_type": "SMS", "sms_delivery_status": "Delivered", "sms_direction": "Outbound", "sms_read_status": "Read", "sms_priority": "Normal", "sms_time": "2023-10-05T17:39:49.000Z", "sms_time_modified": "2023-10-05T17:39:51.193Z", "conversation_id": 827707991992583800, "conversation_uri": "https://platform.ringcentral.com/restapi/v1.0/conversation/827707991992583838"}, {"sms_id": 2170684181043, "sms_message": "Hey Mifrah!\n\nMary here with Re/Max Premier Realty and FindBusinesses4Sale, we\u00c2\u00b4re a Canadian Business Marketplace.\n\nI have just left you a Voicemail.\n\nPlease contact me using this number when you are free:\n(587) 332-0613\n\nThanks!", "to_name": null, "to_location": "Vancouver, BC", "to_availability": "Alive", "from_name": "Duncan Hunter", "from_phone_nuber": "+15873320613", "from_location": "Calgary, AB", "sms_message_type": "SMS", "sms_delivery_status": "Delivered", "sms_direction": "Outbound", "sms_read_status": "Read", "sms_priority": "Normal", "sms_time": "2023-10-05T17:37:19.000Z", "sms_time_modified": "2023-10-05T17:37:20.969Z", "conversation_id": 827707991993880800, "conversation_uri": "https://platform.ringcentral.com/restapi/v1.0/conversation/827707991993880874"}, {"sms_id": 2170673466043, "sms_message": "Babak, my name is Donald with RE/MAX Premier Realty and Find Businesses for Sale. You can call me back on this number.", "to_name": null, "to_location": null, "to_availability": "Alive", "from_name": "Duncan Hunter", "from_phone_nuber": "+15873320613", "from_location": "Calgary, AB", "sms_message_type": "SMS", "sms_delivery_status": "Delivered", "sms_direction": "Outbound", "sms_read_status": "Read", "sms_priority": "Normal", "sms_time": "2023-10-05T16:39:34.000Z", "sms_time_modified": "2023-10-05T16:39:36.410Z", "conversation_id": 827657313412521500, "conversation_uri": "https://platform.ringcentral.com/restapi/v1.0/conversation/827657313412521416"}]